ui_rl/__init__.py
ui_rl/agent.py
ui_rl/cua.py
ui_rl/runner.py
ui_rl/task.py
ui_rl/models/__init__.py
ui_rl/models/uitars15/__init__.py
ui_rl/models/uitars15/dataset.py
ui_rl/models/uitars15/rollout.py
ui_rl/runtime/__init__.py
ui_rl/runtime/docker.py
ui_rl/runtime/kubernetes.py
ui_rl-0.1.1.dist-info/METADATA
ui_rl-0.1.1.dist-info/WHEEL
ui_rl-0.1.1.dist-info/licenses/LICENSE
ui_rl-0.1.1.dist-info/RECORD
