Metadata-Version: 2.4
Name: ui-rl
Version: 0.1.1
Summary: Reinforcement Fine-tuning for Computer Use models
Project-URL: Repository, https://github.com/TobiasNorlund/ui-rl
Project-URL: Issues, https://github.com/TobiasNorlund/ui-rl/issues
Author-email: Tobias Norlund <tobias@norlund.se>
License-Expression: Apache-2.0
License-File: LICENSE
Classifier: Development Status :: 3 - Alpha
Classifier: Intended Audience :: Developers
Classifier: License :: OSI Approved :: Apache Software License
Classifier: Programming Language :: Python :: 3
Classifier: Programming Language :: Python :: 3.12
Requires-Python: >=3.12
Requires-Dist: docker>=7.1.0
Requires-Dist: httpx>=0.28.1
Requires-Dist: kubernetes>=34.1.0
Requires-Dist: pillow>=11.3.0
Requires-Dist: torch>=2.8
Requires-Dist: torchvision>=0.23.0
Requires-Dist: tqdm>=4.67.1
Requires-Dist: transformers>=4.57.3
